openapi_downgrade/__init__.py
openapi_downgrade/cli.py
openapi_downgrade/converter/__init__.py
openapi_downgrade/converter/loader.py
openapi_downgrade/converter/transformer.py
openapi_downgrade/converter/validator.py
openapi_downgrade/converter/warnings.py
openapi_downgrade/converter/rules/anyof_null.py
openapi_downgrade/converter/rules/booleans.py
openapi_downgrade/converter/rules/conditionals_to_oneof.py
openapi_downgrade/converter/rules/const_to_enum.py
openapi_downgrade/converter/rules/emulate_tuple_items.py
openapi_downgrade/converter/rules/examples.py
openapi_downgrade/converter/rules/exclusives.py
openapi_downgrade/converter/rules/fix_null_type.py
openapi_downgrade/converter/rules/jsonschema.py
openapi_downgrade/converter/rules/mixed_types.py
openapi_downgrade/converter/rules/nullable.py
openapi_downgrade/converter/rules/warn_unsupported.py
openapi_downgrade/converter/rules/webhooks.py
openapi_downgrade-1.0.1.dist-info/licenses/LICENSE
tests/run_all_tests_minimal.py
tests/test_full_conversion.py
tests/test_issue_1_datetime.py
tests/test_issue_2_anyof_null.py
tests/test_rules.py
openapi_downgrade-1.0.1.dist-info/METADATA
openapi_downgrade-1.0.1.dist-info/WHEEL
openapi_downgrade-1.0.1.dist-info/entry_points.txt
openapi_downgrade-1.0.1.dist-info/top_level.txt
openapi_downgrade-1.0.1.dist-info/RECORD
