Metadata-Version: 2.4
Name: openapi_downgrade
Version: 1.0.1
Summary: Convert OpenAPI 3.1.x specifications to 3.0.x while preserving logic
Author: Rajesh Roy
Author-email: Rajesh Roy <rajeshroy362000@gmail.com>
License: MIT License
Project-URL: Homepage, https://github.com/RajeshRoy4426/openapi_downgrade_3_0
Project-URL: Repository, https://github.com/RajeshRoy4426/openapi_downgrade_3_0
Project-URL: Issues, https://github.com/RajeshRoy4426/openapi_downgrade_3_0/issues
Keywords: openapi,spec,converter,swagger,openapi3.1,cli,openapi3.0
Classifier: Programming Language :: Python :: 3
Classifier: License :: OSI Approved :: MIT License
Classifier: Operating System :: OS Independent
Classifier: Development Status :: 3 - Alpha
Classifier: Intended Audience :: Developers
Classifier: Topic :: Software Development :: Libraries :: Python Modules
Requires-Python: >=3.7
License-File: LICENSE
Requires-Dist: typer
Requires-Dist: requests
Requires-Dist: pyyaml
Requires-Dist: jsonschema>=4.19.0
Dynamic: license-file
